setup.py
distributions/Binomialdistribution.py
distributions/Gaussiandistribution.py
distributions/Generaldistribution.py
distributions/__init__.py
iduate_probability.egg-info/PKG-INFO
iduate_probability.egg-info/SOURCES.txt
iduate_probability.egg-info/dependency_links.txt
iduate_probability.egg-info/not-zip-safe
iduate_probability.egg-info/top_level.txt