Metadata-Version: 1.0
Name: iduate-probability
Version: 0.1
Summary: probability distributions - Gaussian, Binomial
Home-page: UNKNOWN
Author: UNKNOWN
Author-email: UNKNOWN
License: UNKNOWN
Platform: UNKNOWN
